consts_everywhere/__init__.py
consts_everywhere/consts_everywhere.py
consts_everywhere/wrapt/LICENSE
consts_everywhere/wrapt/__init__.py
consts_everywhere/wrapt/__init__.pyi
consts_everywhere/wrapt/__wrapt__.py
consts_everywhere/wrapt/_wrappers.c
consts_everywhere/wrapt/arguments.py
consts_everywhere/wrapt/decorators.py
consts_everywhere/wrapt/importer.py
consts_everywhere/wrapt/patches.py
consts_everywhere/wrapt/proxies.py
consts_everywhere/wrapt/py.typed
consts_everywhere/wrapt/readme.txt
consts_everywhere/wrapt/weakrefs.py
consts_everywhere/wrapt/wrappers.py
consts_everywhere-1.0.2.dist-info/METADATA
consts_everywhere-1.0.2.dist-info/WHEEL
consts_everywhere-1.0.2.dist-info/RECORD
