Metadata-Version: 2.4
Name: consts-everywhere
Version: 1.0.2
Summary: Create const variables everywhere
Project-URL: Homepage, https://github.com/pyhacks/consts-everywhere
Author-email: pyhacks <enginyildirim111@gmail.com>
Keywords: const,dynamic,runtime
Requires-Dist: assign-overload
Requires-Dist: typeguard
